LICENSE.txt
MANIFEST.in
README.md
pyproject.toml
setup.cfg
setup.py
emulator/__init__.py
emulator/args.py
emulator/em_object.py
emulator/keys.py
emulator/node.py
emulator/opencv.py
emulator/option.py
emulator/adb/AdbWinApi.dll
emulator/adb/AdbWinUsbApi.dll
emulator/adb/adb.exe
emulator/base64/base64.exe
emulator/dump/window_dump.xml
emulator/sed/libiconv2.dll
emulator/sed/libintl3.dll
emulator/sed/regex2.dll
emulator/sed/sed.exe
emulator_Thw_Fix.egg-info/PKG-INFO
emulator_Thw_Fix.egg-info/SOURCES.txt
emulator_Thw_Fix.egg-info/dependency_links.txt
emulator_Thw_Fix.egg-info/requires.txt
emulator_Thw_Fix.egg-info/top_level.txt